python_sample_03_08_2023/__init__.py
python_sample_03_08_2023/basic_math.py
python_sample_03_08_2023-0.1.3.dist-info/LICENSE
python_sample_03_08_2023-0.1.3.dist-info/METADATA
python_sample_03_08_2023-0.1.3.dist-info/WHEEL
python_sample_03_08_2023-0.1.3.dist-info/RECORD
