Metadata-Version: 2.1
Name: python-sample-03-08-2023
Version: 0.1.3
Summary: template python project to get started
Author: Soliton
Requires-Python: >=3.9,<4.0
Classifier: Programming Language :: Python :: 3
Classifier: Programming Language :: Python :: 3.9
Classifier: Programming Language :: Python :: 3.10
Classifier: Programming Language :: Python :: 3.11
